dasdo/__init__.py
dasdo/__main__.py
dasdo/chat.py
dasdo/chat_member.py
dasdo/chat_settings.py
dasdo/entry.py
dasdo/item.py
dasdo/item_bid.py
dasdo/item_create.py
dasdo/item_settings.py
dasdo/main.py
dasdo/user.py
dasdo/user_settings.py
dasdo/utils/__init__.py
dasdo/utils/config.py
dasdo/utils/currency.py
dasdo/utils/model.py
dasdo-0.1.2.dist-info/entry_points.txt
dasdo-0.1.2.dist-info/WHEEL
dasdo-0.1.2.dist-info/METADATA
dasdo-0.1.2.dist-info/RECORD
