Metadata-Version: 2.1
Name: dasdo
Version: 0.1.2
Summary: 
Author: Hadi Zo
Author-email: hadi.zolfaghaari@gmail.com
Requires-Python: >=3.8,<4.0
Classifier: Programming Language :: Python :: 3
Classifier: Programming Language :: Python :: 3.8
Classifier: Programming Language :: Python :: 3.9
Requires-Dist: Babel (>=2.9.0,<3.0.0)
Requires-Dist: pymongo (>=3.11.3,<4.0.0)
Requires-Dist: python-telegram-bot (>=13.4.1,<14.0.0)
Requires-Dist: sentry-sdk (>=1.0.0,<2.0.0)
